freckles_cli/__init__.py
freckles_cli/freckles_base_cli.py
freckles_cli/frkl.info
freckles_cli/freckelize/__init__.py
freckles_cli/freckelize/freckelize_cli.py
freckles_cli/freckelize/freckelize_init_plugin.py
freckles_cli/frecklecute/__init__.py
freckles_cli/frecklecute/frecklecute_cli.py
freckles_cli/freckles_cli/__init__.py
freckles_cli/freckles_cli/freckles_cli.py
freckles_cli/plugins/__init__.py
freckles_cli/plugins/freckles_cli_plugin_config.py
freckles_cli/plugins/freckles_cli_plugin_context.py
freckles_cli/plugins/freckles_cli_plugin_doc.py
freckles_cli/plugins/freckles_cli_plugin_list.py
freckles_cli/plugins/freckles_cli_plugin_run.py
freckles_cli/plugins/freckles_cli_plugin_runs.py
freckles_cli/plugins/freckles_cli_plugin_self.py
freckles_cli/plugins/freckles_cli_plugin_ssh.py
freckles_cli-1.0.2.dist-info/AUTHORS.rst
freckles_cli-1.0.2.dist-info/LICENSE
freckles_cli-1.0.2.dist-info/METADATA
freckles_cli-1.0.2.dist-info/WHEEL
freckles_cli-1.0.2.dist-info/entry_points.txt
freckles_cli-1.0.2.dist-info/top_level.txt
freckles_cli-1.0.2.dist-info/RECORD
